signal_ICT_AumLathigara_92400133189/__init__.py
signal_ICT_AumLathigara_92400133189/operations.py
signal_ICT_AumLathigara_92400133189/trigonometric_signals.py
signal_ICT_AumLathigara_92400133189/unitary_signals.py
signal_ict_aumlathigara_92400133189-2.0.0.dist-info/licenses/LICENSE
signal_ict_aumlathigara_92400133189-2.0.0.dist-info/METADATA
signal_ict_aumlathigara_92400133189-2.0.0.dist-info/WHEEL
signal_ict_aumlathigara_92400133189-2.0.0.dist-info/top_level.txt
signal_ict_aumlathigara_92400133189-2.0.0.dist-info/RECORD
